{"LE1 4SX":{"postcode":"LE1 4SX","location":{"verticalAccuracy":-1,"speed":-1,"longitude":-1.1361376000000001,"horizontalAccuracy":100,"course":-1,"latitude":52.6373107,"timestamp":589883223.62920594,"altitude":0}},"LE5 0AE":{"postcode":"LE5 0AE","location":{"verticalAccuracy":-1,"speed":-1,"longitude":-1.1246404000000001,"horizontalAccuracy":100,"course":-1,"latitude":52.637334199999998,"timestamp":589883192.90808403,"altitude":0}},"LE1 3UD":{"postcode":"LE1 3UD","location":{"verticalAccuracy":-1,"speed":-1,"longitude":-1.1320063,"horizontalAccuracy":100,"course":-1,"latitude":52.642962199999999,"timestamp":589883170.31372797,"altitude":0}},"LE1 5XY":{"postcode":"LE1 5XY","location":{"verticalAccuracy":-1,"speed":-1,"longitude":-1.1356025999999999,"horizontalAccuracy":100,"course":-1,"latitude":52.629215799999997,"timestamp":589883188.80529201,"altitude":0}},"LE4 5NU":{"postcode":"LE4 5NU","location":{"verticalAccuracy":-1,"speed":-1,"longitude":-1.1351315,"horizontalAccuracy":100,"course":-1,"latitude":52.652361599999999,"timestamp":589883184.65521598,"altitude":0}},"LE2 4AL":{"postcode":"LE2 4AL","location":{"verticalAccuracy":-1,"speed":-1,"longitude":-1.0968819000000001,"horizontalAccuracy":100,"course":-1,"latitude":52.603197600000001,"timestamp":589883166.20512295,"altitude":0}},"LE1 1RD":{"postcode":"LE1 1RD","location":{"verticalAccuracy":-1,"speed":-1,"longitude":-1.1285350000000001,"horizontalAccuracy":100,"course":-1,"latitude":52.634692899999997,"timestamp":589883168.26261103,"altitude":0}},"LE1 5WH":{"postcode":"LE1 5WH","location":{"verticalAccuracy":-1,"speed":-1,"longitude":-1.1405413,"horizontalAccuracy":100,"course":-1,"latitude":52.632029600000003,"timestamp":589883201.10826099,"altitude":0}},"LE1 6SL":{"postcode":"LE1 6SL","location":{"verticalAccuracy":-1,"speed":-1,"longitude":-1.1312575,"horizontalAccuracy":100,"course":-1,"latitude":52.633013800000001,"timestamp":589883190.85872304,"altitude":0}},"CV13 0LP":{"postcode":"CV13 0LP","location":{"verticalAccuracy":-1,"speed":-1,"longitude":-1.3906292,"horizontalAccuracy":100,"course":-1,"latitude":52.625677199999998,"timestamp":589883176.45283794,"altitude":0}},"LE1 5PZ":{"postcode":"LE1 5PZ","location":{"verticalAccuracy":-1,"speed":-1,"longitude":-1.1379147999999999,"horizontalAccuracy":100,"course":-1,"latitude":52.6341052,"timestamp":589883203.15662706,"altitude":0}},"LE1 7GR":{"postcode":"LE1 7GR","location":{"verticalAccuracy":-1,"speed":-1,"longitude":-1.1237963,"horizontalAccuracy":100,"course":-1,"latitude":52.6285448,"timestamp":589883213.39711595,"altitude":0}},"LE1 6QL":{"postcode":"LE1 6QL","location":{"verticalAccuracy":-1,"speed":-1,"longitude":-1.1319494000000001,"horizontalAccuracy":100,"course":-1,"latitude":52.632398500000001,"timestamp":589883186.75628901,"altitude":0}},"LE1 5DB":{"postcode":"LE1 5DB","location":{"verticalAccuracy":-1,"speed":-1,"longitude":-1.1352226999999999,"horizontalAccuracy":100,"course":-1,"latitude":52.6342474,"timestamp":589883229.78206396,"altitude":0}},"LE2 7FL":{"postcode":"LE2 7FL","location":{"verticalAccuracy":-1,"speed":-1,"longitude":-1.1414998000000001,"horizontalAccuracy":100,"course":-1,"latitude":52.620043899999999,"timestamp":589883178.50209796,"altitude":0}},"LE1 1SB":{"postcode":"LE1 1SB","location":{"verticalAccuracy":-1,"speed":-1,"longitude":-1.1272070999999999,"horizontalAccuracy":100,"course":-1,"latitude":52.636076600000003,"timestamp":589883194.95732796,"altitude":0}},"LE11 2TY":{"postcode":"LE11 2TY","location":{"verticalAccuracy":-1,"speed":-1,"longitude":-1.2044478999999999,"horizontalAccuracy":100,"course":-1,"latitude":52.770281199999999,"timestamp":589883233.89257598,"altitude":0}},"LE2 8BU":{"postcode":"LE2 8BU","location":{"verticalAccuracy":-1,"speed":-1,"longitude":-1.1534118,"horizontalAccuracy":100,"course":-1,"latitude":52.603904,"timestamp":589883172.35981405,"altitude":0}},"LE2 7TR":{"postcode":"LE2 7TR","location":{"verticalAccuracy":-1,"speed":-1,"longitude":-1.1341534,"horizontalAccuracy":100,"course":-1,"latitude":52.624035999999997,"timestamp":589883205.20380497,"altitude":0}},"LE1 9BH":{"postcode":"LE1 9BH","location":{"verticalAccuracy":-1,"speed":-1,"longitude":-1.1380353999999999,"horizontalAccuracy":100,"course":-1,"latitude":52.629467300000002,"timestamp":589883207.25183499,"altitude":0}},"LE1 6ZH":{"postcode":"LE1 6ZH","location":{"verticalAccuracy":-1,"speed":-1,"longitude":-1.1334039,"horizontalAccuracy":100,"course":-1,"latitude":52.632067599999999,"timestamp":589883227.72740996,"altitude":0}},"LE16 7WB":{"postcode":"LE16 7WB","location":{"verticalAccuracy":-1,"speed":-1,"longitude":-0.93924390000000002,"horizontalAccuracy":100,"course":-1,"latitude":52.495392500000001,"timestamp":589883215.44077098,"altitude":0}},"LE1 6RU":{"postcode":"LE1 6RU","location":{"verticalAccuracy":-1,"speed":-1,"longitude":-1.1329646,"horizontalAccuracy":100,"course":-1,"latitude":52.6311204,"timestamp":589883197.01193595,"altitude":0}},"LE11 3QF":{"postcode":"LE11 3QF","location":{"verticalAccuracy":-1,"speed":-1,"longitude":-1.2455608,"horizontalAccuracy":100,"course":-1,"latitude":52.761928599999997,"timestamp":589883219.53192699,"altitude":0}},"LE19 1RP":{"postcode":"LE19 1RP","location":{"verticalAccuracy":-1,"speed":-1,"longitude":-1.1912830999999999,"horizontalAccuracy":100,"course":-1,"latitude":52.6118357,"timestamp":589883182.60267496,"altitude":0}},"LE1 1QW":{"postcode":"LE1 1QW","location":{"verticalAccuracy":-1,"speed":-1,"longitude":-1.1252783,"horizontalAccuracy":100,"course":-1,"latitude":52.634983599999998,"timestamp":589883164.16614997,"altitude":0}},"LE2 8EB":{"postcode":"LE2 8EB","location":{"verticalAccuracy":-1,"speed":-1,"longitude":-1.1447875000000001,"horizontalAccuracy":100,"course":-1,"latitude":52.606717500000002,"timestamp":589883225.68029594,"altitude":0}},"LE4 0AA":{"postcode":"LE4 0AA","location":{"verticalAccuracy":-1,"speed":-1,"longitude":-1.1428673,"horizontalAccuracy":100,"course":-1,"latitude":52.643805399999998,"timestamp":589883231.83507597,"altitude":0}},"LE18 2DR":{"postcode":"LE18 2DR","location":{"verticalAccuracy":-1,"speed":-1,"longitude":-1.114852,"horizontalAccuracy":100,"course":-1,"latitude":52.5834112,"timestamp":589883199.06082594,"altitude":0}},"LE3 5BJ":{"postcode":"LE3 5BJ","location":{"verticalAccuracy":-1,"speed":-1,"longitude":-1.1439233,"horizontalAccuracy":100,"course":-1,"latitude":52.636656899999998,"timestamp":589883211.34800398,"altitude":0}},"LE1 4AN":{"postcode":"LE1 4AN","location":{"verticalAccuracy":-1,"speed":-1,"longitude":-1.1375853,"horizontalAccuracy":100,"course":-1,"latitude":52.6358289,"timestamp":589883217.48648798,"altitude":0}},"LE13 0PB":{"postcode":"LE13 0PB","location":{"verticalAccuracy":-1,"speed":-1,"longitude":-0.89221289999999998,"horizontalAccuracy":100,"course":-1,"latitude":52.770339399999997,"timestamp":589883221.58410096,"altitude":0}},"LE19 0AL":{"postcode":"LE19 0AL","location":{"verticalAccuracy":-1,"speed":-1,"longitude":-1.2090612999999999,"horizontalAccuracy":100,"course":-1,"latitude":52.583313500000003,"timestamp":589883180.55229104,"altitude":0}},"LE1 7PA":{"postcode":"LE1 7PA","location":{"verticalAccuracy":-1,"speed":-1,"longitude":-1.1210188999999999,"horizontalAccuracy":100,"course":-1,"latitude":52.625584500000002,"timestamp":589883174.40791094,"altitude":0}},"LE1 1RE":{"postcode":"LE1 1RE","location":{"verticalAccuracy":-1,"speed":-1,"longitude":-1.127991,"horizontalAccuracy":100,"course":-1,"latitude":52.634554100000003,"timestamp":589883209.29981697,"altitude":0}}}