{"CV3 1HB":{"postcode":"CV3 1HB","location":{"verticalAccuracy":-1,"speed":-1,"longitude":-1.4752091000000001,"horizontalAccuracy":100,"course":-1,"latitude":52.4063303,"timestamp":594142303.43700302,"altitude":0}},"CV35 8QL":{"postcode":"CV35 8QL","location":{"verticalAccuracy":-1,"speed":-1,"longitude":-1.6235767000000001,"horizontalAccuracy":100,"course":-1,"latitude":52.2882696,"timestamp":594142270.51982796,"altitude":0}},"CV37 8PL":{"postcode":"CV37 8PL","location":{"verticalAccuracy":-1,"speed":-1,"longitude":-1.7780563,"horizontalAccuracy":100,"course":-1,"latitude":52.123219300000002,"timestamp":594142293.18550205,"altitude":0}},"CV1 5FD":{"postcode":"CV1 5FD","location":{"verticalAccuracy":-1,"speed":-1,"longitude":-1.5003702999999999,"horizontalAccuracy":100,"course":-1,"latitude":52.412087100000001,"timestamp":594142340.36802804,"altitude":0}},"CV7 9DR":{"postcode":"CV7 9DR","location":{"verticalAccuracy":-1,"speed":-1,"longitude":-1.4058326999999999,"horizontalAccuracy":100,"course":-1,"latitude":52.433215300000001,"timestamp":594142301.38464904,"altitude":0}},"CV1 5ED":{"postcode":"CV1 5ED","location":{"verticalAccuracy":-1,"speed":-1,"longitude":-1.4938794,"horizontalAccuracy":100,"course":-1,"latitude":52.407472499999997,"timestamp":594142299.336169,"altitude":0}},"CV32 5LA":{"postcode":"CV32 5LA","location":{"verticalAccuracy":-1,"speed":-1,"longitude":-1.5387257999999999,"horizontalAccuracy":100,"course":-1,"latitude":52.292086400000002,"timestamp":594142350.68562198,"altitude":0}},"CV32 5AA":{"postcode":"CV32 5AA","location":{"verticalAccuracy":-1,"speed":-1,"longitude":-1.5358046999999999,"horizontalAccuracy":100,"course":-1,"latitude":52.288200099999997,"timestamp":594142266.41779697,"altitude":0}},"CV7 9JU":{"postcode":"CV7 9JU","location":{"verticalAccuracy":-1,"speed":-1,"longitude":-1.4034234999999999,"horizontalAccuracy":100,"course":-1,"latitude":52.430811900000002,"timestamp":594142311.64069295,"altitude":0}},"CV34 6UW":{"postcode":"CV34 6UW","location":{"verticalAccuracy":-1,"speed":-1,"longitude":-1.5637536000000001,"horizontalAccuracy":100,"course":-1,"latitude":52.275648199999999,"timestamp":594142326.00312603,"altitude":0}},"CV1 5QP":{"postcode":"CV1 5QP","location":{"verticalAccuracy":-1,"speed":-1,"longitude":-1.5061277,"horizontalAccuracy":100,"course":-1,"latitude":52.407191599999997,"timestamp":594142262.31475401,"altitude":0}},"CV10 0UX":{"postcode":"CV10 0UX","location":{"verticalAccuracy":-1,"speed":-1,"longitude":-1.5238429,"horizontalAccuracy":100,"course":-1,"latitude":52.542206399999998,"timestamp":594142336.26740897,"altitude":0}},"CV37 8DX":{"postcode":"CV37 8DX","location":{"verticalAccuracy":-1,"speed":-1,"longitude":-1.6785399000000001,"horizontalAccuracy":100,"course":-1,"latitude":52.156264100000001,"timestamp":594142282.93603504,"altitude":0}},"CV1 5EN":{"postcode":"CV1 5EN","location":{"verticalAccuracy":-1,"speed":-1,"longitude":-1.5003702999999999,"horizontalAccuracy":100,"course":-1,"latitude":52.412087100000001,"timestamp":594142321.90368903,"altitude":0}},"CV23 9LF":{"postcode":"CV23 9LF","location":{"verticalAccuracy":-1,"speed":-1,"longitude":-1.3313545,"horizontalAccuracy":100,"course":-1,"latitude":52.340344100000003,"timestamp":594142276.77666795,"altitude":0}},"CV11 5BU":{"postcode":"CV11 5BU","location":{"verticalAccuracy":-1,"speed":-1,"longitude":-1.4710198000000001,"horizontalAccuracy":100,"course":-1,"latitude":52.523029800000003,"timestamp":594142328.05377495,"altitude":0}},"CV7 7NH":{"postcode":"CV7 7NH","location":{"verticalAccuracy":-1,"speed":-1,"longitude":-1.6379203,"horizontalAccuracy":100,"course":-1,"latitude":52.435007200000001,"timestamp":594142338.31604195,"altitude":0}},"CV34 4JS":{"postcode":"CV34 4JS","location":{"verticalAccuracy":-1,"speed":-1,"longitude":-1.5865880000000001,"horizontalAccuracy":100,"course":-1,"latitude":52.285134200000002,"timestamp":594142346.56973505,"altitude":0}},"CV37 0HR":{"postcode":"CV37 0HR","location":{"verticalAccuracy":-1,"speed":-1,"longitude":-1.7202051,"horizontalAccuracy":100,"course":-1,"latitude":52.201879900000002,"timestamp":594142268.46695495,"altitude":0}},"CV1 5FB":{"postcode":"CV1 5FB","location":{"verticalAccuracy":-1,"speed":-1,"longitude":-1.5000631,"horizontalAccuracy":100,"course":-1,"latitude":52.405314099999998,"timestamp":594142289.08419299,"altitude":0}},"CV1 5EB":{"postcode":"CV1 5EB","location":{"verticalAccuracy":-1,"speed":-1,"longitude":-1.4953936000000001,"horizontalAccuracy":100,"course":-1,"latitude":52.407460899999997,"timestamp":594142334.21505594,"altitude":0}},"CV34 4SA":{"postcode":"CV34 4SA","location":{"verticalAccuracy":-1,"speed":-1,"longitude":-1.5901071,"horizontalAccuracy":100,"course":-1,"latitude":52.281865000000003,"timestamp":594142272.57060504,"altitude":0}},"CV1 3BH":{"postcode":"CV1 3BH","location":{"verticalAccuracy":-1,"speed":-1,"longitude":-1.5245886,"horizontalAccuracy":100,"course":-1,"latitude":52.406026599999997,"timestamp":594142284.98588097,"altitude":0}},"CV1 5RN":{"postcode":"CV1 5RN","location":{"verticalAccuracy":-1,"speed":-1,"longitude":-1.5076803000000001,"horizontalAccuracy":100,"course":-1,"latitude":52.407692500000003,"timestamp":594142317.79665196,"altitude":0}},"CV8 3DY":{"postcode":"CV8 3DY","location":{"verticalAccuracy":-1,"speed":-1,"longitude":-1.4600915999999999,"horizontalAccuracy":100,"course":-1,"latitude":52.374302100000001,"timestamp":594142330.10071301,"altitude":0}},"CV34 6BF":{"postcode":"CV34 6BF","location":{"verticalAccuracy":-1,"speed":-1,"longitude":-1.5517183999999999,"horizontalAccuracy":100,"course":-1,"latitude":52.277338299999997,"timestamp":594142332.15905094,"altitude":0}},"CV4 7AL":{"postcode":"CV4 7AL","location":{"verticalAccuracy":-1,"speed":-1,"longitude":-1.5648143999999999,"horizontalAccuracy":100,"course":-1,"latitude":52.385809700000003,"timestamp":594142352.73512304,"altitude":0}},"CV34 5RJ":{"postcode":"CV34 5RJ","location":{"verticalAccuracy":-1,"speed":-1,"longitude":-1.6015315000000001,"horizontalAccuracy":100,"course":-1,"latitude":52.287801700000003,"timestamp":594142305.48884106,"altitude":0}},"CV5 6UB":{"postcode":"CV5 6UB","location":{"verticalAccuracy":-1,"speed":-1,"longitude":-1.5523990000000001,"horizontalAccuracy":100,"course":-1,"latitude":52.403240199999999,"timestamp":594142287.03495502,"altitude":0}},"B1 1RN":{"postcode":"B1 1RN","location":{"verticalAccuracy":-1,"speed":-1,"longitude":-1.9069986999999999,"horizontalAccuracy":100,"course":-1,"latitude":52.474999400000002,"timestamp":594142274.62108397,"altitude":0}},"CV10 7SD":{"postcode":"CV10 7SD","location":{"verticalAccuracy":-1,"speed":-1,"longitude":-1.4797933999999999,"horizontalAccuracy":100,"course":-1,"latitude":52.497716799999999,"timestamp":594142319.85166502,"altitude":0}},"CV1 1JD":{"postcode":"CV1 1JD","location":{"verticalAccuracy":-1,"speed":-1,"longitude":-1.5101743999999999,"horizontalAccuracy":100,"course":-1,"latitude":52.410795499999999,"timestamp":594142323.95449495,"altitude":0}},"CV2 2ST":{"postcode":"CV2 2ST","location":{"verticalAccuracy":-1,"speed":-1,"longitude":-1.435905,"horizontalAccuracy":100,"course":-1,"latitude":52.437219300000002,"timestamp":594142307.54093504,"altitude":0}},"CV1 2TT":{"postcode":"CV1 2TT","location":{"verticalAccuracy":-1,"speed":-1,"longitude":-1.5041612,"horizontalAccuracy":100,"course":-1,"latitude":52.402957999999998,"timestamp":594142260.24662602,"altitude":0}},"CV9 1BB":{"postcode":"CV9 1BB","location":{"verticalAccuracy":-1,"speed":-1,"longitude":-1.5472058,"horizontalAccuracy":100,"course":-1,"latitude":52.5773121,"timestamp":594142280.88597798,"altitude":0}},"CV35 8XB":{"postcode":"CV35 8XB","location":{"verticalAccuracy":-1,"speed":-1,"longitude":-1.6622524999999999,"horizontalAccuracy":100,"course":-1,"latitude":52.290031599999999,"timestamp":594142278.83143997,"altitude":0}},"CV1 5RR":{"postcode":"CV1 5RR","location":{"verticalAccuracy":-1,"speed":-1,"longitude":-1.5076134999999999,"horizontalAccuracy":100,"course":-1,"latitude":52.407089900000003,"timestamp":594142344.518677,"altitude":0}},"CV7 9JG":{"postcode":"CV7 9JG","location":{"verticalAccuracy":-1,"speed":-1,"longitude":-1.5099940999999999,"horizontalAccuracy":100,"course":-1,"latitude":52.4549272,"timestamp":594142264.36375797,"altitude":0}},"CV8 3FW":{"postcode":"CV8 3FW","location":{"verticalAccuracy":-1,"speed":-1,"longitude":-1.4062414999999999,"horizontalAccuracy":100,"course":-1,"latitude":52.3830612,"timestamp":594142309.58941495,"altitude":0}},"CV15FB":{"postcode":"CV15FB","location":{"verticalAccuracy":-1,"speed":-1,"longitude":-1.5000631,"horizontalAccuracy":100,"course":-1,"latitude":52.405314099999998,"timestamp":594142297.28415203,"altitude":0}},"CV37 0PY":{"postcode":"CV37 0PY","location":{"verticalAccuracy":-1,"speed":-1,"longitude":-1.6633473999999999,"horizontalAccuracy":100,"course":-1,"latitude":52.226742799999997,"timestamp":594142313.69159806,"altitude":0}},"CV32 7EF":{"postcode":"CV32 7EF","location":{"verticalAccuracy":-1,"speed":-1,"longitude":-1.5217696000000001,"horizontalAccuracy":100,"course":-1,"latitude":52.3063675,"timestamp":594142342.466887,"altitude":0}},"CV32 5LL":{"postcode":"CV32 5LL","location":{"verticalAccuracy":-1,"speed":-1,"longitude":-1.5415158,"horizontalAccuracy":100,"course":-1,"latitude":52.291674700000002,"timestamp":594142348.63050604,"altitude":0}},"CV32 4RA":{"postcode":"CV32 4RA","location":{"verticalAccuracy":-1,"speed":-1,"longitude":-1.532618,"horizontalAccuracy":100,"course":-1,"latitude":52.292889500000001,"timestamp":594142295.23677194,"altitude":0}},"CV3 2AB":{"postcode":"CV3 2AB","location":{"verticalAccuracy":-1,"speed":-1,"longitude":-1.4191781999999999,"horizontalAccuracy":100,"course":-1,"latitude":52.407111299999997,"timestamp":594142291.13229001,"altitude":0}},"GL56 0PE":{"postcode":"GL56 0PE","location":{"verticalAccuracy":-1,"speed":-1,"longitude":-1.6567006,"horizontalAccuracy":100,"course":-1,"latitude":51.992717300000002,"timestamp":594142315.74132204,"altitude":0}}}